[
    {
        "event_id": 1000, 
        "track_id": 10, 
        "track_name": "Session", 
        "room_id": 1134, 
        "room_name": "Hall C.4", 
        "start_time": "2016-12-28T20:00:00+01:00", 
        "duration": 3600, 
        "title": "\"My\" software, like \"my\" hand or like \"my car\"?", 
        "abstract": "Floridi argues that '...in favour of the interpretation of the protection of privacy as protection of personal identity: \u201cmy\u201d in \u201cmy data\u201d is not the same \u201cmy\u201d as in \u201cmy car\u201d, it is the same \u201cmy\u201d as in \u201cmy hand\u201d, because personal information plays a constitutive  role of who I am and can become.\u201d But when my hand is part of a prosthetic arm running on proprietary software, how \u201cmy\u201d is \u201cmy hand\u201d in this case? Is \u201cmy\u201d the same as in \u201cmy car\u201d or as in \u201cmy data\u201d?\n\nOlga Gkotsopoulou is a FSFE trainee and holder of a Law Degree, a LL.M in International Human Rights and Humanitarian Law and a M.A. in History and Theory of Law. In the past, Olga worked for various organizations, including the Hellenic Data Protection Authority, the World Health Organization (WHO), the Institute of International Relations and the Greek Council for Refugees. She is also co-founder of the pro bono organisation, Union for Children's Rights.", 
        "speakers": "Eal"
    }, 
    {
        "event_id": 1001, 
        "track_id": 10, 
        "track_name": "Session", 
        "room_id": 1111, 
        "room_name": "Hall A.1", 
        "start_time": "2016-12-29T17:00:00+01:00", 
        "duration": 7200, 
        "title": "33c3 Regiotreffen", 
        "abstract": "Das allj\u00e4hrliche Regiotreffen auf dem Congress", 
        "speakers": "Telegnom, Sva"
    }, 
    {
        "event_id": 1013, 
        "track_id": 10, 
        "track_name": "Session", 
        "room_id": 1120, 
        "room_name": "Hall B", 
        "start_time": "2016-12-28T19:00:00+01:00", 
        "duration": 7200, 
        "title": "A walk through pEp's tech", 
        "abstract": "p\u2261p engine hackers show you the inner workings of the p\u2261p engine, which is used to drive the crypto used in p\u2261p, message transport and -- most importantly -- automatic key management and synchronization. In this session you also can get technical answers to questions concerning future developments of the p\u2261p technology.", 
        "speakers": "Pf"
    }, 
    {
        "event_id": 1014, 
        "track_id": 10, 
        "track_name": "Session", 
        "room_id": 1131, 
        "room_name": "Hall C.1", 
        "start_time": "2016-12-27T12:00:00+01:00", 
        "duration": 3600, 
        "title": "An UnCivilization Commune ReWilded Life Shared with Squirrels", 
        "abstract": "Looking forward to meet new and old friends interested in UnCivilization! \n\nWe are a group of people interested in intersection of technology & society, politics, activism, art, and critical of techno-optimism. We share a mailing list since 2012, called UnCivilization, inspired (but not otherwise connected to) Dark Mountain \"Uncivilization Manifesto\", as well as Ursula LeGuin, Derrick Jensen, Heather Marsh, John Zerzan, Naomi Klein, Daniel Quinn, Ursula Franklin, and other feminist, anarchist, anti-supremacist authors. \n\nGoal of this meetup is to catch-up, give each other hugs & support, and plan our activities for the next months & years (e.g. another LikaCamp?!)", 
        "speakers": "Becha"
    }, 
    {
        "event_id": 1015, 
        "track_id": 10, 
        "track_name": "Session", 
        "room_id": 1131, 
        "room_name": "Hall C.1", 
        "start_time": "2016-12-30T12:00:00+01:00", 
        "duration": 3600, 
        "title": "An UnCivilization Commune ReWilded Life Shared with Squirrels", 
        "abstract": "Looking forward to meet new and old friends interested in UnCivilization! \n\nWe are a group of people interested in intersection of technology & society, politics, activism, art, and critical of techno-optimism. We share a mailing list since 2012, called UnCivilization, inspired (but not otherwise connected to) Dark Mountain \"Uncivilization Manifesto\", as well as Ursula LeGuin, Derrick Jensen, Heather Marsh, John Zerzan, Naomi Klein, Daniel Quinn, Ursula Franklin, and other feminist, anarchist, anti-supremacist authors. \n\nGoal of this meetup is to catch-up, give each other hugs & support, and plan our activities for the next months & years (e.g. another LikaCamp?!)", 
        "speakers": "Becha"
    }, 
    {
        "event_id": 1016, 
        "track_id": 10, 
        "track_name": "Session", 
        "room_id": 1111, 
        "room_name": "Hall A.1", 
        "start_time": "2016-12-29T12:00:00+01:00", 
        "duration": 5400, 
        "title": "Angewandte konsensdemokratie", 
        "abstract": "thesen: gruppen von menschen lassen sich oft weiter demokratisieren als \"nur\" basisdemokratie zu machen. konsensdemokratie ist nicht nur m\u00f6glich, sondern mittelfristig sogar effizienter und stressfreier. mehr spa\u00df macht sie auch :-)", 
        "speakers": "Uwe premium"
    }, 
    {
        "event_id": 1019, 
        "track_id": 10, 
        "track_name": "Session", 
        "room_id": 1013, 
        "room_name": "Hall 13-14", 
        "start_time": "2016-12-29T20:30:00+01:00", 
        "duration": 3600, 
        "title": "Are decentralized services unable to innovate?", 
        "abstract": "On Signal, XMPP and the future of decentralized services.", 
        "speakers": "Eal"
    }, 
    {
        "event_id": 1021, 
        "track_id": 10, 
        "track_name": "Session", 
        "room_id": 1133, 
        "room_name": "Hall C.3", 
        "start_time": "2016-12-28T15:00:00+01:00", 
        "duration": 3600, 
        "title": "Boat instruments hacking", 
        "abstract": "Session for meeting up and discussing all things around electronics in boats.", 
        "speakers": "Lassekarstensen"
    }, 
    {
        "event_id": 1022, 
        "track_id": 10, 
        "track_name": "Session", 
        "room_id": 1131, 
        "room_name": "Hall C.1", 
        "start_time": "2016-12-27T15:00:00+01:00", 
        "duration": 3600, 
        "title": "CmS L\u00f6tworkshop Vorbesprechung f\u00fcr Helfer", 
        "abstract": "Vorbesprechung f\u00fcr die Helfer des Chaos macht Schule-L\u00f6tworkshops", 
        "speakers": "Djim, Benni, Duisburch"
    }, 
    {
        "event_id": 1023, 
        "track_id": 10, 
        "track_name": "Session", 
        "room_id": 1133, 
        "room_name": "Hall C.3", 
        "start_time": "2016-12-28T12:00:00+01:00", 
        "duration": 3600, 
        "title": "Coder Dojo", 
        "abstract": "", 
        "speakers": "Nana berlin"
    }, 
    {
        "event_id": 1024, 
        "track_id": 10, 
        "track_name": "Session", 
        "room_id": 1134, 
        "room_name": "Hall C.4", 
        "start_time": "2016-12-28T15:00:00+01:00", 
        "duration": 3600, 
        "title": "Coder Dojo", 
        "abstract": "", 
        "speakers": "Nana berlin"
    }, 
    {
        "event_id": 1025, 
        "track_id": 10, 
        "track_name": "Session", 
        "room_id": 1134, 
        "room_name": "Hall C.4", 
        "start_time": "2016-12-28T12:00:00+01:00", 
        "duration": 3600, 
        "title": "Coder Dojo", 
        "abstract": "", 
        "speakers": "Nana berlin"
    }, 
    {
        "event_id": 1026, 
        "track_id": 10, 
        "track_name": "Session", 
        "room_id": 1133, 
        "room_name": "Hall C.3", 
        "start_time": "2016-12-28T11:00:00+01:00", 
        "duration": 3600, 
        "title": "Coder Dojo", 
        "abstract": "", 
        "speakers": "Nana berlin"
    }, 
    {
        "event_id": 1027, 
        "track_id": 10, 
        "track_name": "Session", 
        "room_id": 1134, 
        "room_name": "Hall C.4", 
        "start_time": "2016-12-28T11:00:00+01:00", 
        "duration": 3600, 
        "title": "Coder Dojo", 
        "abstract": "", 
        "speakers": "Nana berlin"
    }, 
    {
        "event_id": 1028, 
        "track_id": 10, 
        "track_name": "Session", 
        "room_id": 1133, 
        "room_name": "Hall C.3", 
        "start_time": "2016-12-28T15:00:00+01:00", 
        "duration": 3600, 
        "title": "Coder Dojo", 
        "abstract": "", 
        "speakers": "Nana berlin"
    }, 
    {
        "event_id": 1035, 
        "track_id": 10, 
        "track_name": "Session", 
        "room_id": 1134, 
        "room_name": "Hall C.4", 
        "start_time": "2016-12-29T15:00:00+01:00", 
        "duration": 7200, 
        "title": "DIY Religion", 
        "abstract": "", 
        "speakers": "Lu cyp"
    }, 
    {
        "event_id": 1038, 
        "track_id": 10, 
        "track_name": "Session", 
        "room_id": 1131, 
        "room_name": "Hall C.1", 
        "start_time": "2016-12-29T17:00:00+01:00", 
        "duration": 3600, 
        "title": "Design in Free Software & Open Source", 
        "abstract": "Design in free software & open source is improving in recent years, but we still have a lot to do. If we want people to use free software, it needs to be as simple & easy to use as proprietary counterparts.\n\nThe Open Source Design collective pushes design in free software. We organize design tracks at well-known events like FOSDEM and FOSSASIA, have a job board to get designers involved, provide open design resources to developers and designers and more.", 
        "speakers": "Eal"
    }, 
    {
        "event_id": 1040, 
        "track_id": 10, 
        "track_name": "Session", 
        "room_id": 1134, 
        "room_name": "Hall C.4", 
        "start_time": "2016-12-29T18:00:00+01:00", 
        "duration": 7200, 
        "title": "Dn42", 
        "abstract": "dn42 is a big dynamic VPN, which employs Internet technologies (BGP, whois database, DNS, etc). Participants connect to each other using network tunnels (GRE, OpenVPN, Tinc, IPsec) and exchange routes thanks to the Border Gateway Protocol. dn42 can be used to learn networking and to connect private networks, such as hackerspaces or community networks. But above all, experimenting with routing in dn42 is fun! This session will start with an introduction to dn42, followed by some short presentations from participants about their projects with dn42 and will finish with free-form discussion about where to take the network in the future.", 
        "speakers": "Irl, Ana"
    }, 
    {
        "event_id": 1041, 
        "track_id": 10, 
        "track_name": "Session", 
        "room_id": 1120, 
        "room_name": "Hall B", 
        "start_time": "2016-12-28T19:45:00+01:00", 
        "duration": 1800, 
        "title": "Engelmeeting", 
        "abstract": "", 
        "speakers": "Knuth"
    }, 
    {
        "event_id": 1042, 
        "track_id": 10, 
        "track_name": "Session", 
        "room_id": 1120, 
        "room_name": "Hall B", 
        "start_time": "2016-12-26T15:00:00+01:00", 
        "duration": 3600, 
        "title": "Engelmeeting", 
        "abstract": "", 
        "speakers": "Knuth"
    }, 
    {
        "event_id": 1043, 
        "track_id": 10, 
        "track_name": "Session", 
        "room_id": 1120, 
        "room_name": "Hall B", 
        "start_time": "2016-12-29T13:00:00+01:00", 
        "duration": 3600, 
        "title": "Engelmeeting", 
        "abstract": "", 
        "speakers": "Knuth"
    }, 
    {
        "event_id": 1044, 
        "track_id": 10, 
        "track_name": "Session", 
        "room_id": 1120, 
        "room_name": "Hall B", 
        "start_time": "2016-12-27T13:00:00+01:00", 
        "duration": 3600, 
        "title": "Engelmeeting", 
        "abstract": "", 
        "speakers": "Knuth"
    }, 
    {
        "event_id": 1045, 
        "track_id": 10, 
        "track_name": "Session", 
        "room_id": 1120, 
        "room_name": "Hall B", 
        "start_time": "2016-12-29T19:45:00+01:00", 
        "duration": 1800, 
        "title": "Engelmeeting", 
        "abstract": "", 
        "speakers": "Knuth"
    }, 
    {
        "event_id": 1046, 
        "track_id": 10, 
        "track_name": "Session", 
        "room_id": 1120, 
        "room_name": "Hall B", 
        "start_time": "2016-12-27T19:45:00+01:00", 
        "duration": 1800, 
        "title": "Engelmeeting", 
        "abstract": "", 
        "speakers": "Knuth"
    }, 
    {
        "event_id": 1047, 
        "track_id": 10, 
        "track_name": "Session", 
        "room_id": 1120, 
        "room_name": "Hall B", 
        "start_time": "2016-12-30T13:00:00+01:00", 
        "duration": 3600, 
        "title": "Engelmeeting", 
        "abstract": "", 
        "speakers": "Knuth"
    }, 
    {
        "event_id": 1048, 
        "track_id": 10, 
        "track_name": "Session", 
        "room_id": 1120, 
        "room_name": "Hall B", 
        "start_time": "2016-12-27T15:00:00+01:00", 
        "duration": 3600, 
        "title": "Engelmeeting", 
        "abstract": "", 
        "speakers": "Knuth"
    }, 
    {
        "event_id": 1049, 
        "track_id": 10, 
        "track_name": "Session", 
        "room_id": 1120, 
        "room_name": "Hall B", 
        "start_time": "2016-12-26T13:00:00+01:00", 
        "duration": 3600, 
        "title": "Engelmeeting", 
        "abstract": "", 
        "speakers": "Knuth"
    }, 
    {
        "event_id": 1050, 
        "track_id": 10, 
        "track_name": "Session", 
        "room_id": 1120, 
        "room_name": "Hall B", 
        "start_time": "2016-12-28T13:00:00+01:00", 
        "duration": 3600, 
        "title": "Engelmeeting", 
        "abstract": "", 
        "speakers": "Knuth"
    }, 
    {
        "event_id": 1051, 
        "track_id": 10, 
        "track_name": "Session", 
        "room_id": 1120, 
        "room_name": "Hall B", 
        "start_time": "2016-12-26T19:45:00+01:00", 
        "duration": 3600, 
        "title": "Engelmeeting", 
        "abstract": "", 
        "speakers": "Knuth"
    }, 
    {
        "event_id": 1052, 
        "track_id": 10, 
        "track_name": "Session", 
        "room_id": 1132, 
        "room_name": "Hall C.2", 
        "start_time": "2016-12-28T14:00:00+01:00", 
        "duration": 3600, 
        "title": "Entscheidungsfindung/Konsens", 
        "abstract": "Schwierigkeiten und L\u00f6sungsans\u00e4tze der konsensbasierten Entscheidungsfindung und andere Fallstricke.\nTheoretische Einf\u00fchrung und Erfahrungsberichte aus 10 Jahren linker Kollektivarbeit.", 
        "speakers": ""
    }, 
    {
        "event_id": 1053, 
        "track_id": 10, 
        "track_name": "Session", 
        "room_id": 1132, 
        "room_name": "Hall C.2", 
        "start_time": "2016-12-29T15:00:00+01:00", 
        "duration": 5400, 
        "title": "Eris Rising", 
        "abstract": "Why hack machines, when you can hack people?\n\nA talk postulating a new type of hacker, the 'Eris': a blackhat sociologist who social engineers groups rather than individuals. Certain group ideologies or behaviors allow easy manipulation, and politically active communities like the hacker community will be in the targets in the coming era.", 
        "speakers": "Colum"
    }, 
    {
        "event_id": 1054, 
        "track_id": 10, 
        "track_name": "Session", 
        "room_id": 1013, 
        "room_name": "Hall 13-14", 
        "start_time": "2016-12-28T20:30:00+01:00", 
        "duration": 3600, 
        "title": "FSaaS", 
        "abstract": "Of all the Free Software business models, Software-as-a-Service (SaaS) is one of the most appealing. Wordpresss blazed a path over a decade ago that few have managed to follow. How do Free Software businesses of this nature work? What are their biggest challenges? And why aren't there more of them? Bring your ideas for a discussion.", 
        "speakers": "Eal"
    }, 
    {
        "event_id": 1055, 
        "track_id": 10, 
        "track_name": "Session", 
        "room_id": 1133, 
        "room_name": "Hall C.3", 
        "start_time": "2016-12-27T17:00:00+01:00", 
        "duration": 5400, 
        "title": "Fiction Writers' Session", 
        "abstract": "Meet-up for all fiction-writing entities: Share your experiences over mate & coffee.", 
        "speakers": "Christina"
    }, 
    {
        "event_id": 1056, 
        "track_id": 10, 
        "track_name": "Session", 
        "room_id": 1230, 
        "room_name": "Hall F", 
        "start_time": "2016-12-29T18:00:00+01:00", 
        "duration": 8100, 
        "title": "Film-Blocker", 
        "abstract": "Blocked for Film Screenings by Content Team", 
        "speakers": ""
    }, 
    {
        "event_id": 1057, 
        "track_id": 10, 
        "track_name": "Session", 
        "room_id": 1230, 
        "room_name": "Hall F", 
        "start_time": "2016-12-29T21:00:00+01:00", 
        "duration": 10800, 
        "title": "Film-Blocker", 
        "abstract": "Blocked for Film Screenings by Content Team", 
        "speakers": ""
    }, 
    {
        "event_id": 1058, 
        "track_id": 10, 
        "track_name": "Session", 
        "room_id": 1111, 
        "room_name": "Hall A.1", 
        "start_time": "2016-12-28T19:30:00+01:00", 
        "duration": 5400, 
        "title": "GNUNet e.V. meeting", 
        "abstract": "GNUNet e.V. meeting", 
        "speakers": "Jeffburdges"
    }, 
    {
        "event_id": 1059, 
        "track_id": 10, 
        "track_name": "Session", 
        "room_id": 1134, 
        "room_name": "Hall C.4", 
        "start_time": "2016-12-27T17:00:00+01:00", 
        "duration": 5400, 
        "title": "GPG Schl\u00fcsselverteilung", 
        "abstract": "Um EndeZuEnde-Verschl\u00fcsselung f\u00fcr die breite Masse nutzbar zu machen, ben\u00f6tigen wir Verfahren, welche mit m\u00f6glichst geringen Aufwand und wenig Vorkenntnisse auch von Laien nutzbar sind. Als Einf\u00fchrung in das Thema, stellt ein kurzer Vortrag die aktuellen Entwicklungen vor, um eine Grundlage f\u00fcr die anschlie\u00dfende Diskussion zu bereiten.", 
        "speakers": ""
    }, 
    {
        "event_id": 1060, 
        "track_id": 10, 
        "track_name": "Session", 
        "room_id": 1013, 
        "room_name": "Hall 13-14", 
        "start_time": "2016-12-29T14:00:00+01:00", 
        "duration": 3600, 
        "title": "Gender diversity in the Free Software community", 
        "abstract": "Only about 3% of contributors in free software are women (even though 25% of software developers are) \u2013 a considerable gap compared to male contributors. There are many reasons for this, and some we want to talk about are: - Is the environment friendly enough? - What can free software projects & companies do to fix the gap? - Why do we need the diversity?\n\nGreta Do\u00e7i is an ICT engineer, active in Wikimedia and the Albanian open source community. Jan-Christoph Borchardt is an interaction designer working on Nextcloud and Open Source Design. They both want to push gender diversity in free & open source software.", 
        "speakers": "Eal"
    }, 
    {
        "event_id": 1061, 
        "track_id": 10, 
        "track_name": "Session", 
        "room_id": 1131, 
        "room_name": "Hall C.1", 
        "start_time": "2016-12-29T14:00:00+01:00", 
        "duration": 5400, 
        "title": "Hackerspace in a graphic novel", 
        "abstract": "Hacker movement in popculture has been reduced to black-hat cliches and even technologically plausible representations like Mr Robot fail to draw its complexities. I'd like to change that with my next project: an online graphic novel featuring a realistic hackerspace community, showcasing people with different and varied approaches to hacking. I'd love to hear your ideas, learn about new sources and existing representations I haven't heard of to create something really worthwhile!", 
        "speakers": "Alxd"
    }, 
    {
        "event_id": 1062, 
        "track_id": 10, 
        "track_name": "Session", 
        "room_id": 1131, 
        "room_name": "Hall C.1", 
        "start_time": "2016-12-28T14:00:00+01:00", 
        "duration": 7200, 
        "title": "Hacking democracy with MEP Marietje Schaake", 
        "abstract": "Member of the European Parliament Marietje Schaake wants to talk about a number of laws that are currently being contemplated in the European Union which might affect the work of hackers, and get your input in order to make them right.", 
        "speakers": "Marietje Schaake"
    }, 
    {
        "event_id": 1063, 
        "track_id": 10, 
        "track_name": "Session", 
        "room_id": 1131, 
        "room_name": "Hall C.1", 
        "start_time": "2016-12-28T18:00:00+01:00", 
        "duration": 7200, 
        "title": "Haftung f\u00fcr Devices und Software gestalten", 
        "abstract": "Billige Webcams, Plasterouter  und Gl\u00fchbirnen in Bonnets bedrohen die Internet-Infrastruktur, f\u00fcr einen Update-Pfad hat der Hersteller keine Kostenstelle vorgesehen. Als L\u00f6sung wird von vielen Seiten eine Herstellerhaftung f\u00fcr Sicherheitsl\u00fccken vorgeschlagen. Wir wollen uns Gedanken machen, wie diese ausgestaltet werden k\u00f6nnen, ohne dass unerw\u00fcnschte Nebenwirkungen wie millionenschwere Haftungsrisiken Open Source-Software oder Endverbraucher bedrohen. Wer soll \u00fcberhaupt haftbar sein, die chinesische Fabrik, der Distributor, der sein Logo draufklebt, der Autor des letzten Commits der Firmware (oder der Software, von der sie abgeleitet ist) oder der Benutzer, der eine alternative Software installiert oder nur die Standardkonfiguration ver\u00e4ndert hat?", 
        "speakers": "Atdotde"
    }, 
    {
        "event_id": 1065, 
        "track_id": 10, 
        "track_name": "Session", 
        "room_id": 1013, 
        "room_name": "Hall 13-14", 
        "start_time": "2016-12-28T16:00:00+01:00", 
        "duration": 3600, 
        "title": "How To Run A Bitcoin Node", 
        "abstract": "Bitcoin is among the world\u2019s most widely deployed decentralized cryptographic systems. We will give a short introduction into the mechanisms behind Bitcoin and then configure a Bitcoin Core node suitable for running at home. Topics that will be covered include:\n* How to get statistics from the network and how to interpret them.\n* How to use the RPC interface to create (multisig-)transactions.\n* How to set limits on resource usage.\n* How to make use of Tor.\n* How to securely store coins.", 
        "speakers": "Nickler"
    }, 
    {
        "event_id": 1066, 
        "track_id": 10, 
        "track_name": "Session", 
        "room_id": 1131, 
        "room_name": "Hall C.1", 
        "start_time": "2016-12-29T15:00:00+01:00", 
        "duration": 1800, 
        "title": "How to Make Humanoid Robots", 
        "abstract": "We will share our knowledge in making humanoid robots with you.\nThe workshop will cover mostly hardware but also software.\nWe will bring some of our robots with us for a hands on.\nIf you want you can also just stop by to ask questions.\nWe will speak mainly in English, but we speak also German and French.", 
        "speakers": "SammyRamone"
    }, 
    {
        "event_id": 1067, 
        "track_id": 10, 
        "track_name": "Session", 
        "room_id": 1131, 
        "room_name": "Hall C.1", 
        "start_time": "2016-12-29T18:15:00+01:00", 
        "duration": 5400, 
        "title": "How to Organize a CryptoParty", 
        "abstract": "**How to CryptoParty**\n\nCryptoParties have been organized all over the world for more than four years. The goal of this session is to help anyone interested to organize one themselves.", 
        "speakers": "Dawning-sun"
    }, 
    {
        "event_id": 1068, 
        "track_id": 10, 
        "track_name": "Session", 
        "room_id": 1013, 
        "room_name": "Hall 13-14", 
        "start_time": "2016-12-27T16:00:00+01:00", 
        "duration": 10800, 
        "title": "How to Survive 33C3 CryptoParty", 
        "abstract": "", 
        "speakers": "Yuvadm"
    }, 
    {
        "event_id": 1069, 
        "track_id": 10, 
        "track_name": "Session", 
        "room_id": 1013, 
        "room_name": "Hall 13-14", 
        "start_time": "2016-12-28T13:00:00+01:00", 
        "duration": 7200, 
        "title": "IT-solutions for humanitarian crisis problems", 
        "abstract": "Syrien, ein Land welches innerhalb von 5 Jahren von einem hohen technischen Level zur\u00fcck in die Steinzeit gebombt wurde. Weite Teile des Landes sind ohne Internet. Telefonnetze sind von unterschiedlicher Qualit\u00e4t und Verf\u00fcgbarkeit. Viele Regionen des Landes sind auf Grund der Vorherrschaft unterschiedlichster Milizen nicht passierbar f\u00fcr Helfer*innen in der humanit\u00e4ren Arbeit. \nNur ein Beispiel, wo es neue L\u00f6sungen braucht f\u00fcr humanit\u00e4re Notlagen. Wenn wir die Betroffenen nicht selbst erreichen k\u00f6nnen, wie k\u00f6nnen wir dann doch mit innovativen Methoden vor Ort Hilfe leisten?\n\nCADUS e.V. arbeitet seit \u00fcber 2 Jahren in verschiedenen Krisenregionen. In dem Workshop dient CADUS als Fallgeberin f\u00fcr akute Problemstellungen in den Regionen vor Ort. In Arbeitsgruppen wollen wir L\u00f6sungsm\u00f6glichkeiten f\u00fcr (Teil-)Probleme erarbeiten, und deren Durchf\u00fchrbarkeit direkt mit Menschen diskutieren, die den Bogen von der Theorie zur Praxis schlagen k\u00f6nnen.", 
        "speakers": "Cadus"
    }, 
    {
        "event_id": 1070, 
        "track_id": 10, 
        "track_name": "Session", 
        "room_id": 1013, 
        "room_name": "Hall 13-14", 
        "start_time": "2016-12-30T16:15:00+01:00", 
        "duration": 7200, 
        "title": "IT-solutions for humanitarian crisis problems", 
        "abstract": "Syrien, ein Land welches innerhalb von 5 Jahren von einem hohen technischen Level zur\u00fcck in die Steinzeit gebombt wurde. Weite Teile des Landes sind ohne Internet. Telefonnetze sind von unterschiedlicher Qualit\u00e4t und Verf\u00fcgbarkeit. Viele Regionen des Landes sind auf Grund der Vorherrschaft unterschiedlichster Milizen nicht passierbar f\u00fcr Helfer*innen in der humanit\u00e4ren Arbeit. \nNur ein Beispiel, wo es neue L\u00f6sungen braucht f\u00fcr humanit\u00e4re Notlagen. Wenn wir die Betroffenen nicht selbst erreichen k\u00f6nnen, wie k\u00f6nnen wir dann doch mit innovativen Methoden vor Ort Hilfe leisten?\n\nCADUS e.V. arbeitet seit \u00fcber 2 Jahren in verschiedenen Krisenregionen. In dem Workshop dient CADUS als Fallgeberin f\u00fcr akute Problemstellungen in den Regionen vor Ort. In Arbeitsgruppen wollen wir L\u00f6sungsm\u00f6glichkeiten f\u00fcr (Teil-)Probleme erarbeiten, und deren Durchf\u00fchrbarkeit direkt mit Menschen diskutieren, die den Bogen von der Theorie zur Praxis schlagen k\u00f6nnen.", 
        "speakers": "Cadus"
    }, 
    {
        "event_id": 1071, 
        "track_id": 10, 
        "track_name": "Session", 
        "room_id": 1134, 
        "room_name": "Hall C.4", 
        "start_time": "2016-12-28T15:00:00+01:00", 
        "duration": 3600, 
        "title": "Implications of the EU copyright reform on Free Software", 
        "abstract": "The meeting is designed to bring together advocates to\ndiscuss and exchange the views about the implications of on-going\ncopyright reform on Free Software, in particular the inclusion of\nfar-reaching DRM measures in the latest proposal for the directive and\nhow this can have an impact on Free Software.", 
        "speakers": "Eal"
    }, 
    {
        "event_id": 1072, 
        "track_id": 10, 
        "track_name": "Session", 
        "room_id": 1131, 
        "room_name": "Hall C.1", 
        "start_time": "2016-12-27T18:00:00+01:00", 
        "duration": 5400, 
        "title": "Introduction to LEAP encryption access project and Pixelated", 
        "abstract": "We talk about the current state of VPN and encrypted email services and the use cases for providers and end users.", 
        "speakers": "Varac, Kali, Zara"
    }, 
    {
        "event_id": 1074, 
        "track_id": 10, 
        "track_name": "Session", 
        "room_id": 1133, 
        "room_name": "Hall C.3", 
        "start_time": "2016-12-29T12:00:00+01:00", 
        "duration": 5400, 
        "title": "IoT by beginners for beginners", 
        "abstract": "Getting started with the Internet of Things using the ESP8266 WiFi SoC. A basic how-to for beginners by beginners: \n- which software u need to install - how to flash the NoceMCU Firmware - how to start with your first small LUA script, connecting the WiFi module to the world - bring your laptop with you and try out ... (Prerequisites: Java, Python2.7)", 
        "speakers": "TobiOrNotTobi, Trema"
    }, 
    {
        "event_id": 1075, 
        "track_id": 10, 
        "track_name": "Session", 
        "room_id": 1230, 
        "room_name": "Hall F", 
        "start_time": "2016-12-28T01:00:00+01:00", 
        "duration": 82800, 
        "title": "Junghackertag", 
        "abstract": "L\u00f6tworkshop von Chaos Macht Schule f\u00fcr Junghacker", 
        "speakers": "Djim, Duisburch, Benni, Cbass, Stean"
    }, 
    {
        "event_id": 1080, 
        "track_id": 10, 
        "track_name": "Session", 
        "room_id": 1131, 
        "room_name": "Hall C.1", 
        "start_time": "2016-12-28T16:00:00+01:00", 
        "duration": 2700, 
        "title": "Kopf aus dem Sand - Wie du ohne Parteien die Politik beeinflussen kannst!", 
        "abstract": "#KopfausdemSand - Wenn du denkst Unterschriftenlisten und nie beachtete Demos sind die einzigen Methoden um die Politik in \u00d6sterreich, Deutschland oder der EU zu beeinflussen, dann m\u00f6chte ich dir hier einen \u00dcberblick geben welche M\u00f6glichkeiten es noch gibt um die Gesetzgebung und Verwaltung zu unseren Gunsten zu beeinflussen.\nMan kann zwar Gesetze selbst nicht schaffen, aber der Einfluss ist noch lange nicht bei 0! Wir haben sowohl die Netzneutralit\u00e4t Gro\u00dfteils gerettet als auch schon einmal die Vorratsdatenspeicherung gekippt.\nF\u00fcr Neueinsteiger, Menschen und andere Lebensformen die meinen sie k\u00f6nnten noch etwas Neues lernen.", 
        "speakers": "Eest9"
    }, 
    {
        "event_id": 1081, 
        "track_id": 10, 
        "track_name": "Session", 
        "room_id": 1230, 
        "room_name": "Hall F", 
        "start_time": "2016-12-29T20:15:00+01:00", 
        "duration": 2700, 
        "title": "Kurzfilm-Screening", 
        "abstract": "Kurzfilm-Screening 61 Tage - Deutschland auf der Flucht  -  Was w\u00e4re, wenn WIR fliehen m\u00fcssten!?", 
        "speakers": "DerNiko"
    }, 
    {
        "event_id": 1082, 
        "track_id": 10, 
        "track_name": "Session", 
        "room_id": 1132, 
        "room_name": "Hall C.2", 
        "start_time": "2016-12-28T17:00:00+01:00", 
        "duration": 7200, 
        "title": "LEAP Platform for vpn + LEAP and Pixelated platform for email providers", 
        "abstract": "We'll show you how to setup a LEAP provider to self-host a vpn and/or encrypted email service.", 
        "speakers": "Varac"
    }, 
    {
        "event_id": 1087, 
        "track_id": 10, 
        "track_name": "Session", 
        "room_id": 1133, 
        "room_name": "Hall C.3", 
        "start_time": "2016-12-28T18:00:00+01:00", 
        "duration": 5400, 
        "title": "Mate", 
        "abstract": "You probably know Club Mate and Flora Mate, as they are available at the 33c3. But there are more kinds of Mate and we will taste them!\nYou can bring own bottles by yourself, too. It is possible that we will not have all existing brands.", 
        "speakers": "Leodin, Xilent"
    }, 
    {
        "event_id": 1088, 
        "track_id": 10, 
        "track_name": "Session", 
        "room_id": 1132, 
        "room_name": "Hall C.2", 
        "start_time": "2016-12-29T18:00:00+01:00", 
        "duration": 5400, 
        "title": "Meier 3", 
        "abstract": "", 
        "speakers": ""
    }, 
    {
        "event_id": 1089, 
        "track_id": 10, 
        "track_name": "Session", 
        "room_id": 1013, 
        "room_name": "Hall 13-14", 
        "start_time": "2016-12-29T17:00:00+01:00", 
        "duration": 7200, 
        "title": "Meine erste IFG-Anfrage", 
        "abstract": "Wie bekomme ich schnell und einfach Informationen, die bei Beh\u00f6rden lagern - Vertr\u00e4ge, Vermerke und E-Mails zwischen Beamten? Wie kann ich sie f\u00fcr politisches Engagement nutzen? Und was mache ich, wenn Beh\u00f6rden mich mit Geb\u00fchren und Gesetzestexten abschrecken wollen? Ich stelle die Plattform FragDenStaat vor und einige wirksame Werkzeuge, mit denen ihr genau die Infos bekommt, die ihr haben wollt.", 
        "speakers": "Eal"
    }, 
    {
        "event_id": 1090, 
        "track_id": 10, 
        "track_name": "Session", 
        "room_id": 1013, 
        "room_name": "Hall 13-14", 
        "start_time": "2016-12-28T00:15:00+01:00", 
        "duration": 6000, 
        "title": "Network concepts introduction & wireshark workshop", 
        "abstract": "'''Ever wondered how webpages arrive in your browser? How zmap works? Want to get your first hands-on experience using ''wireshark''?'''\n\nTo learn all that you need to learn the basic networking concepts. You're in luck as this is a hands-on networking workshop preceded by a lecture. We will cover such topics as the ISO/OSI model, Ethernet, IP, TCP, UDP, routing, and wireshark.", 
        "speakers": "Kirils"
    }, 
    {
        "event_id": 1091, 
        "track_id": 10, 
        "track_name": "Session", 
        "room_id": 1134, 
        "room_name": "Hall C.4", 
        "start_time": "2016-12-30T14:30:00+01:00", 
        "duration": 10800, 
        "title": "Neuropil", 
        "abstract": "making and breaking of neuropil :-)\nwe would like to set up an neuropil network together with the participants and try to identify vulnerabilities ...", 
        "speakers": "Stephan.schwichtenberg"
    }, 
    {
        "event_id": 1092, 
        "track_id": 10, 
        "track_name": "Session", 
        "room_id": 1132, 
        "room_name": "Hall C.2", 
        "start_time": "2016-12-28T16:00:00+01:00", 
        "duration": 3600, 
        "title": "NewPipe", 
        "abstract": "NewPipe is a Free Youtube/Streaming app for Android. This talk will be about how NewPipe works, and what the features of NewPipe will be. The app was created as a hobby project one year ago, but slowly evolves.", 
        "speakers": "Eal"
    }, 
    {
        "event_id": 1093, 
        "track_id": 10, 
        "track_name": "Session", 
        "room_id": 1134, 
        "room_name": "Hall C.4", 
        "start_time": "2016-12-29T11:00:00+01:00", 
        "duration": 10800, 
        "title": "Numerical Weather Prediction Tutorial", 
        "abstract": "A workshop about running your own Numerical Weather Prediction (NWP) model.", 
        "speakers": "Tecer"
    }, 
    {
        "event_id": 1096, 
        "track_id": 10, 
        "track_name": "Session", 
        "room_id": 1134, 
        "room_name": "Hall C.4", 
        "start_time": "2016-12-28T16:00:00+01:00", 
        "duration": 5400, 
        "title": "Open Education Workshop", 
        "abstract": "Despite high expectations, \"digital education\" has not much advanced beyond sharing single-purpose worksheets as pdf. Existing Open Educational Resources (OER) often tend to reinforce current teaching scenarios and top-down structures, missing out on the potential for new forms of participation. To prepare new education projects, we invite you to share your experiences and ideas: How can digital methods / concepts / tools contribute to a more inclusive pedagogy, enabling and motivating learners for co-creation? What else can we do within existing frameworks, and how to approach it effectively in class?", 
        "speakers": "NMarkus, PeterVanPan"
    }, 
    {
        "event_id": 1097, 
        "track_id": 10, 
        "track_name": "Session", 
        "room_id": 1133, 
        "room_name": "Hall C.3", 
        "start_time": "2016-12-29T14:00:00+01:00", 
        "duration": 10800, 
        "title": "Open Science Workshop", 
        "abstract": "Do you think science is as open, transparent and reproducible as it could be? Are we using the full potential of digitalization and the internet for our research. Are non-scientist sufficiently aware of and embedded into the scientific process? We want to discuss all this and want to hear your voice and experiences! Open Access, Open Data, Open Notebooks, Open Source, Open Educational Resources Citizen science - those topics and more will be in the center of this participant-driven meeting. More importantly we want to connect people interested in a more open and better science.", 
        "speakers": "Konrad, Aleimba, Rupi, Iimog"
    }, 
    {
        "event_id": 1098, 
        "track_id": 10, 
        "track_name": "Session", 
        "room_id": 1134, 
        "room_name": "Hall C.4", 
        "start_time": "2016-12-27T15:00:00+01:00", 
        "duration": 7200, 
        "title": "PCB design for beginners using KiCad", 
        "abstract": "You will learn how to create basic schematics, select footprints and finally design the actual PCB using KiCad.", 
        "speakers": "Kbeckmann"
    }, 
    {
        "event_id": 1099, 
        "track_id": 10, 
        "track_name": "Session", 
        "room_id": 1013, 
        "room_name": "Hall 13-14", 
        "start_time": "2016-12-28T11:00:00+01:00", 
        "duration": 5400, 
        "title": "Pixel Art Workshop", 
        "abstract": "You'll get an introduction to the techniques and principles of pixel art, as well as useful hints, learning resources and software recommendations. After that, we'll paint a few 16x16 pixel-sized pictures together. If you use Twitter, you'll like this format, as well! :)", 
        "speakers": "Blinry"
    }, 
    {
        "event_id": 1100, 
        "track_id": 10, 
        "track_name": "Session", 
        "room_id": 1134, 
        "room_name": "Hall C.4", 
        "start_time": "2016-12-28T11:00:00+01:00", 
        "duration": 7200, 
        "title": "Pixelated hands-on", 
        "abstract": "--- session will be in English, German and Brazilian Portuguese ---\n\nWe are organising this hands-on session to invite people to learn about Pixelated, an open source solution for automatised email encryption.\nIn the session we will invite you too try things out, to give us feedback, and we will show you how to install and set up Pixelated on your machine or on a remote server.\n\nLooking forward to see you there and as a future contributor. ;)", 
        "speakers": "Varac, Zara"
    }, 
    {
        "event_id": 1101, 
        "track_id": 10, 
        "track_name": "Session", 
        "room_id": 1111, 
        "room_name": "Hall A.1", 
        "start_time": "2016-12-29T16:00:00+01:00", 
        "duration": 3600, 
        "title": "PoParty", 
        "abstract": "Come and fetch the first PoPCoin at 33c3!", 
        "speakers": "Ineiti"
    }, 
    {
        "event_id": 1102, 
        "track_id": 10, 
        "track_name": "Session", 
        "room_id": 1120, 
        "room_name": "Hall B", 
        "start_time": "2016-12-27T18:00:00+01:00", 
        "duration": 3600, 
        "title": "Privacy by default with pretty Easy privacy (p\u2261p)", 
        "abstract": "The pretty Easy privacy project (p\u2261p) is a project to turn the cyberpunk movement's dream into reality that everyone should be able to protect his/her privacy using technical tools. Overall p\u2261p is about changing today's default of digital written communications from unencrypted, unanonymized and unverified to encrypted, anonymized and verified. p\u2261p's vision is to offer an automatic and easy to use solution to make all end-to-end written digital communications over the Internet \u2018Private and Secure by Default and Design\u2018. With that 'unencrypted' e-mails become the exception not the norm. The p\u2261p project aims at encrypting existing written digital communications and does not force users to switch to platform-centric or other crypto solutions, in which users are likely to be locked.", 
        "speakers": "Eal"
    }, 
    {
        "event_id": 1103, 
        "track_id": 10, 
        "track_name": "Session", 
        "room_id": 1013, 
        "room_name": "Hall 13-14", 
        "start_time": "2016-12-28T21:30:00+01:00", 
        "duration": 1800, 
        "title": "Prototype Fund - 1.2 Million Euros for Free Software Projects", 
        "abstract": "The Prototype Fund supports the implementation of ideas in civic tech, data literacy, data security and software infrastructure. With a grant of up to \u20ac30,000, software developers, hackers and creatives can write code and develop open source prototypes over a period of six months.\n\nApplying is as easy as possible and the next deadline at the begin of February. Come, hear and ask us everything about the Prototype Fund.", 
        "speakers": "Eal"
    }, 
    {
        "event_id": 1104, 
        "track_id": 10, 
        "track_name": "Session", 
        "room_id": 1120, 
        "room_name": "Hall B", 
        "start_time": "2016-12-27T16:00:00+01:00", 
        "duration": 7200, 
        "title": "Queer Feminist Geeks Gathering", 
        "abstract": "A meetup for all the queer feminist geek folk.\n\nWe will talk a bit about our assembly and what we are doing there, exchange projects and ideas, and network with each other. This meetup is open to people of all genders, but please be mindful of how much space you are taking up. Especially if you are white, male, straight and cis, please try to actively listen instead of talking. \n\nThis is our Code of Conduct: https://events.ccc.de/congress/2015/wiki/Projects:Code_of_Conduct_of_the_Queer_Feminist_Geek_Assembly", 
        "speakers": "Obaz, UMT, CoopDot"
    }, 
    {
        "event_id": 1105, 
        "track_id": 10, 
        "track_name": "Session", 
        "room_id": 1131, 
        "room_name": "Hall C.1", 
        "start_time": "2016-12-27T16:30:00+01:00", 
        "duration": 5400, 
        "title": "Queer Feminist Geeks Gathering", 
        "abstract": "A meetup for all the queer feminist geek folk.\n\nWe will talk a bit about our assembly and what we are doing there, exchange projects and ideas, and network with each other. This meetup is open to people of all genders, but please be mindful of how much space you are taking up. Especially if you are white, male, straight and cis, please try to actively listen instead of talking. \n\nThis is our Code of Conduct: https://events.ccc.de/congress/2015/wiki/Projects:Code_of_Conduct_of_the_Queer_Feminist_Geek_Assembly", 
        "speakers": "Obaz, UMT, CoopDot"
    }, 
    {
        "event_id": 1106, 
        "track_id": 10, 
        "track_name": "Session", 
        "room_id": 1134, 
        "room_name": "Hall C.4", 
        "start_time": "2016-12-27T19:30:00+01:00", 
        "duration": 5400, 
        "title": "Radio Lockdown Directive", 
        "abstract": "This will be a meeting for political organisations that work on the radio lockdown directive.", 
        "speakers": "Eal"
    }, 
    {
        "event_id": 1107, 
        "track_id": 10, 
        "track_name": "Session", 
        "room_id": 1134, 
        "room_name": "Hall C.4", 
        "start_time": "2016-12-28T19:00:00+01:00", 
        "duration": 3600, 
        "title": "Radio Lockdown", 
        "abstract": "The Radio Equipment Directive (2014/53/EU) contains a provision requiring hardware manufacturers to check all software installable on their devices. Community WiFi projects heavily rely on (free software) firmware they modify for their purposes and install on consumer-grade hardware. Action is needed to mitigate this threat, but there's a promising course of action: Community WiFi initiatives of Europe, unite!", 
        "speakers": "KaerF"
    }, 
    {
        "event_id": 1108, 
        "track_id": 10, 
        "track_name": "Session", 
        "room_id": 1013, 
        "room_name": "Hall 13-14", 
        "start_time": "2016-12-28T02:00:00+01:00", 
        "duration": 3600, 
        "title": "Skillconvention a", 
        "abstract": "all travelers with a certain skill will be invited to these sessions.", 
        "speakers": "Reisende"
    }, 
    {
        "event_id": 1109, 
        "track_id": 10, 
        "track_name": "Session", 
        "room_id": 1111, 
        "room_name": "Hall A.1", 
        "start_time": "2016-12-28T01:00:00+01:00", 
        "duration": 3600, 
        "title": "Skillconvention a", 
        "abstract": "all travelers with a certain skill will be invited to these sessions.", 
        "speakers": "Reisende"
    }, 
    {
        "event_id": 1110, 
        "track_id": 10, 
        "track_name": "Session", 
        "room_id": 1111, 
        "room_name": "Hall A.1", 
        "start_time": "2016-12-28T02:00:00+01:00", 
        "duration": 3600, 
        "title": "Skillconvention a", 
        "abstract": "all travelers with a certain skill will be invited to these sessions.", 
        "speakers": "Reisende"
    }, 
    {
        "event_id": 1111, 
        "track_id": 10, 
        "track_name": "Session", 
        "room_id": 1013, 
        "room_name": "Hall 13-14", 
        "start_time": "2016-12-28T03:00:00+01:00", 
        "duration": 3600, 
        "title": "Skillconvention a", 
        "abstract": "all travelers with a certain skill will be invited to these sessions.", 
        "speakers": "Reisende"
    }, 
    {
        "event_id": 1112, 
        "track_id": 10, 
        "track_name": "Session", 
        "room_id": 1111, 
        "room_name": "Hall A.1", 
        "start_time": "2016-12-29T00:30:00+01:00", 
        "duration": 3600, 
        "title": "Skillconvention b", 
        "abstract": "all travelers of a certain skill will be invented to join their respective session", 
        "speakers": "Reisende"
    }, 
    {
        "event_id": 1113, 
        "track_id": 10, 
        "track_name": "Session", 
        "room_id": 1013, 
        "room_name": "Hall 13-14", 
        "start_time": "2016-12-29T00:30:00+01:00", 
        "duration": 3600, 
        "title": "Skillconvention b", 
        "abstract": "all travelers of a certain skill will be invented to join their respective session", 
        "speakers": "Reisende"
    }, 
    {
        "event_id": 1114, 
        "track_id": 10, 
        "track_name": "Session", 
        "room_id": 1111, 
        "room_name": "Hall A.1", 
        "start_time": "2016-12-29T01:30:00+01:00", 
        "duration": 3600, 
        "title": "Skillconvention b", 
        "abstract": "all travelers of a certain skill will be invented to join their respective session", 
        "speakers": "Reisende"
    }, 
    {
        "event_id": 1115, 
        "track_id": 10, 
        "track_name": "Session", 
        "room_id": 1013, 
        "room_name": "Hall 13-14", 
        "start_time": "2016-12-29T01:30:00+01:00", 
        "duration": 3600, 
        "title": "Skillconvention b", 
        "abstract": "all travelers of a certain skill will be invented to join their respective session", 
        "speakers": "Reisende"
    }, 
    {
        "event_id": 1116, 
        "track_id": 10, 
        "track_name": "Session", 
        "room_id": 1013, 
        "room_name": "Hall 13-14", 
        "start_time": "2016-12-29T02:30:00+01:00", 
        "duration": 3600, 
        "title": "Skillconvention b", 
        "abstract": "all travelers of a certain skill will be invented to join their respective session", 
        "speakers": "Reisende"
    }, 
    {
        "event_id": 1117, 
        "track_id": 10, 
        "track_name": "Session", 
        "room_id": 1013, 
        "room_name": "Hall 13-14", 
        "start_time": "2016-12-30T00:30:00+01:00", 
        "duration": 3600, 
        "title": "Skillconvention c", 
        "abstract": "all travelers of a certain skill will be invited to join their respective convention", 
        "speakers": "Reisende"
    }, 
    {
        "event_id": 1118, 
        "track_id": 10, 
        "track_name": "Session", 
        "room_id": 1111, 
        "room_name": "Hall A.1", 
        "start_time": "2016-12-30T00:30:00+01:00", 
        "duration": 3600, 
        "title": "Skillconvention c", 
        "abstract": "all travelers of a certain skill will be invited to join their respective convention", 
        "speakers": "Reisende"
    }, 
    {
        "event_id": 1119, 
        "track_id": 10, 
        "track_name": "Session", 
        "room_id": 1013, 
        "room_name": "Hall 13-14", 
        "start_time": "2016-12-30T01:30:00+01:00", 
        "duration": 3600, 
        "title": "Skillconvention c", 
        "abstract": "all travelers of a certain skill will be invited to join their respective convention", 
        "speakers": "Reisende"
    }, 
    {
        "event_id": 1120, 
        "track_id": 10, 
        "track_name": "Session", 
        "room_id": 1120, 
        "room_name": "Hall B", 
        "start_time": "2016-12-29T20:45:00+01:00", 
        "duration": 10800, 
        "title": "Social Engineering Poetry Slam", 
        "abstract": "Listen to social engineering attack stories from fellow hackers. Presented in a poetry slam style! Or present your social engineering experience or fictional story on how to deceive or manipulate people.", 
        "speakers": "Uebelhacker"
    }, 
    {
        "event_id": 1121, 
        "track_id": 10, 
        "track_name": "Session", 
        "room_id": 1131, 
        "room_name": "Hall C.1", 
        "start_time": "2016-12-29T20:15:00+01:00", 
        "duration": 9000, 
        "title": "Social Engineering Poetry Slam", 
        "abstract": "Listen to social engineering attack stories from fellow hackers. Presented in a poetry slam style! Or present your social engineering experience or fictional story on how to deceive or manipulate people.", 
        "speakers": "Uebelhacker"
    }, 
    {
        "event_id": 1122, 
        "track_id": 10, 
        "track_name": "Session", 
        "room_id": 1132, 
        "room_name": "Hall C.2", 
        "start_time": "2016-12-27T16:00:00+01:00", 
        "duration": 10800, 
        "title": "Space Hacking", 
        "abstract": "Grenzen\u00fcberschreitende Aktionen an scheinbar unzug\u00e4nglichen Orten, ein\nSchiff als Arena schwimmender Spontandemos,  Hausfassaden, die innerhalb\nweniger Minuten in Farbe getaucht werden, Wandbild-Brigaden als\ninternationalistische Politikarbeit und mittendrin: ein Raum f\u00fcr\nKulturKunstPartyPolitik\u2026\n\nWie nehmen wir uns den \u00f6ffentlichen Raum, umgehen seine Vorschriften und\nReglementierungen?\nWie schaffen wir Orte f\u00fcr Kollektivit\u00e4t und basisdemokratisches\nZusammenleben?\nWelche kulturellen Praxen halten wir den Spielregeln der freien\nMarktwirtschaft entgegen?\n\nPr\u00e4sentation mit Wermke/Leinkauf, Freimeutern, Urban Divas,\nInterbrigadas, Graffitiarchiv und Mensch Meier.", 
        "speakers": "Jona"
    }, 
    {
        "event_id": 1126, 
        "track_id": 10, 
        "track_name": "Session", 
        "room_id": 1111, 
        "room_name": "Hall A.1", 
        "start_time": "2016-12-29T13:30:00+01:00", 
        "duration": 9000, 
        "title": "Taler workshop", 
        "abstract": "We shall teach visitors to integrate the GNU Taler merchant software for anonymous web payments into existing web platforms.  \n\nWe're happy to advise visitors interested in setting up GNU Taler exchanges as well, including discussions about integrating the exchange with blockchain based currencies. We will not have teaching materials handy for the exchange software however.", 
        "speakers": "Jeffburdges"
    }, 
    {
        "event_id": 1127, 
        "track_id": 10, 
        "track_name": "Session", 
        "room_id": 1013, 
        "room_name": "Hall 13-14", 
        "start_time": "2016-12-29T16:00:00+01:00", 
        "duration": 3600, 
        "title": "The Federation", 
        "abstract": "This talk will give a short introduction to \"The Federation\" of decentral social networks as alternatives to the big walled gardens.\n\nWith a short historical overview of how it all began almost a decade ago with Laconica, followed by Diaspora and Mistpark.\nWho is part of \"The Federation\" today?\nHow are those projects glued together?\nWhat is the current state of free software alternatives like Diaspora, Friendica, GNU Social, Hubzilla, Media Goblin, pump.io and compatible networks.\nHow might the future be looking with the recent work by W3C Social WG.", 
        "speakers": "Eal"
    }, 
    {
        "event_id": 1128, 
        "track_id": 10, 
        "track_name": "Session", 
        "room_id": 1013, 
        "room_name": "Hall 13-14", 
        "start_time": "2016-12-28T18:00:00+01:00", 
        "duration": 3600, 
        "title": "The user-friendly guide to mobile freedom", 
        "abstract": "A guide to use your multiple devices with Free Software and synchronize them", 
        "speakers": "Eal"
    }, 
    {
        "event_id": 1129, 
        "track_id": 10, 
        "track_name": "Session", 
        "room_id": 1120, 
        "room_name": "Hall B", 
        "start_time": "2016-12-28T21:00:00+01:00", 
        "duration": 7200, 
        "title": "Tor", 
        "abstract": "Session should be used to connect with all the people who work for the various projects within or related with tor.", 
        "speakers": "Julius"
    }, 
    {
        "event_id": 1130, 
        "track_id": 10, 
        "track_name": "Session", 
        "room_id": 1134, 
        "room_name": "Hall C.4", 
        "start_time": "2016-12-28T17:30:00+01:00", 
        "duration": 5400, 
        "title": "Train the CryptoParty Trainer", 
        "abstract": "Training our own trainers we can help grow the CryptoParty. In this session we'd like to share concepts and ideas on what works.", 
        "speakers": "Dawning-sun"
    }, 
    {
        "event_id": 1131, 
        "track_id": 10, 
        "track_name": "Session", 
        "room_id": 1013, 
        "room_name": "Hall 13-14", 
        "start_time": "2016-12-30T15:10:00+01:00", 
        "duration": 3000, 
        "title": "Translation meetings", 
        "abstract": "The translation angels (interpreters) meet twice per day to self-organise (day 0, evening to day 4, afternoon)", 
        "speakers": "Sebalis"
    }, 
    {
        "event_id": 1132, 
        "track_id": 10, 
        "track_name": "Session", 
        "room_id": 1013, 
        "room_name": "Hall 13-14", 
        "start_time": "2016-12-27T15:10:00+01:00", 
        "duration": 3000, 
        "title": "Translation meetings", 
        "abstract": "The translation angels (interpreters) meet twice per day to self-organise (day 0, evening to day 4, afternoon)", 
        "speakers": "Sebalis"
    }, 
    {
        "event_id": 1133, 
        "track_id": 10, 
        "track_name": "Session", 
        "room_id": 1013, 
        "room_name": "Hall 13-14", 
        "start_time": "2016-12-28T19:40:00+01:00", 
        "duration": 3000, 
        "title": "Translation meetings", 
        "abstract": "The translation angels (interpreters) meet twice per day to self-organise (day 0, evening to day 4, afternoon)", 
        "speakers": "Sebalis"
    }, 
    {
        "event_id": 1134, 
        "track_id": 10, 
        "track_name": "Session", 
        "room_id": 1013, 
        "room_name": "Hall 13-14", 
        "start_time": "2016-12-26T20:00:00+01:00", 
        "duration": 5400, 
        "title": "Translation meetings", 
        "abstract": "The translation angels (interpreters) meet twice per day to self-organise (day 0, evening to day 4, afternoon)", 
        "speakers": "Sebalis"
    }, 
    {
        "event_id": 1135, 
        "track_id": 10, 
        "track_name": "Session", 
        "room_id": 1013, 
        "room_name": "Hall 13-14", 
        "start_time": "2016-12-29T19:40:00+01:00", 
        "duration": 3000, 
        "title": "Translation meetings", 
        "abstract": "The translation angels (interpreters) meet twice per day to self-organise (day 0, evening to day 4, afternoon)", 
        "speakers": "Sebalis"
    }, 
    {
        "event_id": 1136, 
        "track_id": 10, 
        "track_name": "Session", 
        "room_id": 1013, 
        "room_name": "Hall 13-14", 
        "start_time": "2016-12-27T19:40:00+01:00", 
        "duration": 3000, 
        "title": "Translation meetings", 
        "abstract": "The translation angels (interpreters) meet twice per day to self-organise (day 0, evening to day 4, afternoon)", 
        "speakers": "Sebalis"
    }, 
    {
        "event_id": 1137, 
        "track_id": 10, 
        "track_name": "Session", 
        "room_id": 1013, 
        "room_name": "Hall 13-14", 
        "start_time": "2016-12-28T15:10:00+01:00", 
        "duration": 3000, 
        "title": "Translation meetings", 
        "abstract": "The translation angels (interpreters) meet twice per day to self-organise (day 0, evening to day 4, afternoon)", 
        "speakers": "Sebalis"
    }, 
    {
        "event_id": 1138, 
        "track_id": 10, 
        "track_name": "Session", 
        "room_id": 1013, 
        "room_name": "Hall 13-14", 
        "start_time": "2016-12-29T15:10:00+01:00", 
        "duration": 3000, 
        "title": "Translation meetings", 
        "abstract": "The translation angels (interpreters) meet twice per day to self-organise (day 0, evening to day 4, afternoon)", 
        "speakers": "Sebalis"
    }, 
    {
        "event_id": 1139, 
        "track_id": 10, 
        "track_name": "Session", 
        "room_id": 1133, 
        "room_name": "Hall C.3", 
        "start_time": "2016-12-28T13:00:00+01:00", 
        "duration": 5400, 
        "title": "UMUM", 
        "abstract": "Meeting of users and not-yet-users of MikroTik devices  to get in contact and share their wisdom. This meeting is private organized!", 
        "speakers": "Njumaen"
    }, 
    {
        "event_id": 1140, 
        "track_id": 10, 
        "track_name": "Session", 
        "room_id": 1134, 
        "room_name": "Hall C.4", 
        "start_time": "2016-12-28T19:00:00+01:00", 
        "duration": 3600, 
        "title": "Veripeditus AR Game Framework", 
        "abstract": "Veripeditus is the first free and open source framework that enables everyone to develop augmented reality mobile games like Ingress or Pok\u00e9mon Go. It brings the creative side of such games to everyone, including, but not limited to, class rooms, along with a great new way of learning programming skills with Python.\n\nPresented by Nik, a 26 year-old software developer and network admin from Bonn, but better known as head of Teckids e.V., a youth organisation establishing a FOSS community among children.", 
        "speakers": "Eal"
    }, 
    {
        "event_id": 1141, 
        "track_id": 10, 
        "track_name": "Session", 
        "room_id": 1120, 
        "room_name": "Hall B", 
        "start_time": "2016-12-28T14:00:00+01:00", 
        "duration": 18000, 
        "title": "We Fix the Net", 
        "abstract": "We Fix the Net session will include talks on developing secure alternatives to current internet protocols.  We might hold an organized discussion or panel as well.  This session is organized by GNUnet and pEp, and acts as a successor to the YBTI sessions of previous years.", 
        "speakers": "Jeffburdges"
    }, 
    {
        "event_id": 1143, 
        "track_id": 10, 
        "track_name": "Session", 
        "room_id": 1013, 
        "room_name": "Hall 13-14", 
        "start_time": "2016-12-28T17:00:00+01:00", 
        "duration": 3600, 
        "title": "What makes a secure mobile messenger? -- A comparison of WhatsApp competitors", 
        "abstract": "There are an increasing number of mobile SMS-like applications that offer different levels of crypto and privacy features. This talk will give an overview over some popular and some less well known apps and discuss certain aspects that get too little attention in mainstream debates.", 
        "speakers": "Eal"
    }, 
    {
        "event_id": 1144, 
        "track_id": 10, 
        "track_name": "Session", 
        "room_id": 1134, 
        "room_name": "Hall C.4", 
        "start_time": "2016-12-28T13:00:00+01:00", 
        "duration": 3600, 
        "title": "Wikidata query and visualization", 
        "abstract": "This is a talk about visualization with wikidata, how wikidata\u200b works and how people can contribute\u200b, also what are some of the project where people can get involve\u200b\u200b. We will learn what is a query and how you can use them to visualize and combine information of data from wikidata.\n\nGreta Do\u00e7i is an ICT engineer student who contributes to Open Source/Free Software since 2013. She is one of the board members of Wikimedians of Albanian User Group. Greta is currently working as an security support assistant at a government institution.", 
        "speakers": "Eal"
    }, 
    {
        "event_id": 1145, 
        "track_id": 10, 
        "track_name": "Session", 
        "room_id": 1134, 
        "room_name": "Hall C.4", 
        "start_time": "2016-12-28T14:00:00+01:00", 
        "duration": 3600, 
        "title": "Wikidata, the encyclopedia by bots, for bots", 
        "abstract": "This workshop aims to explain what Wikidata is, and how to use it. We'll explore the data mode, web API, and query interface.\n\nWikidata is the world's largest free general purpose knowledge base. As a Wikimedia-run sister project of Wikipedia, it provides machine readable information about just about anything. It's the encyclopedia by bots, for bots.", 
        "speakers": "Brightbyte"
    }, 
    {
        "event_id": 1146, 
        "track_id": 10, 
        "track_name": "Session", 
        "room_id": 1133, 
        "room_name": "Hall C.3", 
        "start_time": "2016-12-27T20:00:00+01:00", 
        "duration": 10800, 
        "title": "Wordclock", 
        "abstract": "Wir bauen wieder Wordclocks.\nBitte unbedingt vorher per mail an fabian@fabmail.org registrieren, da die Teilnehmerzahl auf 15 Personen beschr\u00e4nkt ist.", 
        "speakers": "Fabianurban"
    }, 
    {
        "event_id": 1147, 
        "track_id": 10, 
        "track_name": "Session", 
        "room_id": 1133, 
        "room_name": "Hall C.3", 
        "start_time": "2016-12-28T20:00:00+01:00", 
        "duration": 10800, 
        "title": "Wordclock", 
        "abstract": "Wir bauen wieder Wordclocks.\nBitte unbedingt vorher per mail an fabian@fabmail.org registrieren, da die Teilnehmerzahl auf 15 Personen beschr\u00e4nkt ist.", 
        "speakers": "Fabianurban"
    }, 
    {
        "event_id": 1148, 
        "track_id": 10, 
        "track_name": "Session", 
        "room_id": 1133, 
        "room_name": "Hall C.3", 
        "start_time": "2016-12-28T15:00:00+01:00", 
        "duration": 7200, 
        "title": "Your own Glowing Micropet!", 
        "abstract": "Enter this Workshop to get a sample of your very own glow-in-the-dark pet! We will be playing around with Aliibvibrio Fischeri, a bioluminescent bacterium living all over the world's oceans.", 
        "speakers": "A.Vibrio.F."
    }
]